{
	"basics": {
	"name": "Zachary Chaikin",
	"label": "Graduate",
	"picture": "https://zchaikin.github.io/images/zachaikin.PNG",
	"email": "zchaikin@hawaii.edu",
	"phone": "(808) 640-5535",
	"website": "https://zchaikin.github.io",
	"summary": "I am a May 2023 graduate with a B.S. in Computer Science from the University of Hawaii.",
	"location": {
	"address": "",
	"postalCode": "",
	"city": "Honolulu",
	"countryCode": "USA",
	"region": "Hawaii"
	},
	"profiles": [
		{
		"network": "github",
		"username": "zchaikin",
		"url": "http://github.com/zchaikin"
		},
		{
		"network": "linkedin",
		"username": "Zachary Chaikin",
		"url": "http://www.linkedin.com/in/zachary-chaikin-8aa9221bb"
		}
		]
	},
	"interests": [
		{
		"name": "Artificial Intelligence",
		"keywords": []
		},
		{
		"name": "Augmented Reality",
		"keywords": []
		},
		{
		"name": "Computer Science",
		"keywords": []
		},
		{
		"name": "Data Visualizations",
		"keywords": []
		},
		{
		"name": "Education",
		"keywords": []
		},
		{
		"name": "Game Design/Development",
		"keywords": []
		},
		{
		"name": "Robotics",
		"keywords": []
		},
		{
		"name": "Software Engineering",
		"keywords": []
		},
		{
		"name": "Sports Analytics/Science",
		"keywords": []
		},
		{
		"name": "Virtual Reality",
		"keywords": []
		}
	],
	"skills": [
		{
		"name": "Frameworks/Languages",
		"level": "",
		"keywords": [
		"C",
		"C++",
		"CSS",
		"HTML",
		"Java",
		"Javascript",
		"Meteor",
		"Python",
		"React",
		"Semantic UI",
		"Unity"
		]
		},
		{
		"name": "OS and Tools",
		"level": "",
		"keywords": [
		"Eclipse",
		"Git/Github",
		"IntelliJ",
		"MacOS",
		"Oculus",
		"Plotly",
		"Unix",
		"Visual Studio",
		"Windows"
		]
		}
	],
	"education": [
		{
		"institution": "The University of Hawaii, Honolulu, HI",
		"area": "B.S. Computer Science",
		"startDate": "2019-08-26",
		"endDate": "2023-05-13",
		"gpa": "3.61",
		"courses": [
		"ICS 111 (Intro to Computer Science I)",
		"ICS 141 (Discrete Math I)",
		"ICS 211 (Intro to Computer Science II)",
		"ICS 212 (Intro to C/C++ Programming)",
		"ICS 241 (Discrete Math II)",
		"ICS 311 (Algorithms)",
		"ICS 312 (Machine-Level & Systems Programing)",
		"ICS 313 (Programming Language Theory)",
		"ICS 314 (Software Engineering I)",
		"ICS 332 (Operating Systems)",
		"ICS 427 (Software Quality Assurance)",
		"ICS 464 (Human-Computer Interaction I)",
		"ICS 484 (Data Visualization)",
		"ICS 485 (Video Game Design)",
		"ICS 486 (Virtual & Augmented Reality Programming)"
		]
		}
	],
	"work": [
    		{
      		"company": "Hawaii Dinosaur Volleyball Tournament, Kauai",
      		"position": "Assistant and Website Manager",
      		"website": "https://hawaiidinosaurvolleyball.com/",
     		"startDate": "2014-03-01",
      		"endDate": "Present",
      		"summary": "Assist in setting up, communicating, and coordinating 120+ teams across six courts over three days. Also, create and manage content for the Hawaii Dinosaur Volleyball Tournament website.",
      		"highlights": [
       		"The Ability to work and thrive in a high-pressure environment.",
		"Design and manage a website to optimize user experience.",
		"Efficiently communicate and coordinate with 120+ teams."
      		]
    		},
    		{
      		"company": "Miscellaneous Volleyball Tournaments, Queens Beach",
      		"position": "Co-Director",
      		"website": "",
      		"startDate": "2020-01-01",
      		"endDate": "Present",
      		"summary": "Design and organize brackets for game schedules using web applications. Also, co-direct and run the tournaments.",
      		"highlights": [
        	"Design and organize tournament formats for enhanced competition.",
		"Valuable expertise in event planning and time management."
      		]
    		},
    		{
      		"company": "Summer High School Volleyball Assistant, Kamuela",
      		"position": "Player Development",
      		"website": "",
      		"startDate": "2018-01-01",
      		"endDate": "2020-01-01",
      		"summary": "Assist with player development of high school volleyball players to achieve individual and team growth.",
      		"highlights": [
        	"Develop strong communication and strong qualities of leadership.",
		"Mentor student-athletes to help them achieve individual and team growth."
      		]
    		}
  	]
}
